mlflow_extensions/__init__.py
mlflow_extensions/version.py
mlflow_extensions/databricks/__init__.py
mlflow_extensions/databricks/deploy/__init__.py
mlflow_extensions/databricks/deploy/ez_deploy.py
mlflow_extensions/databricks/deploy/ez_deploy_lite.py
mlflow_extensions/databricks/deploy/ez_deploy_lite_entrypoint.py
mlflow_extensions/databricks/deploy/ez_deploy_ray_serve.py
mlflow_extensions/databricks/deploy/ez_deploy_ray_serve_entrypoint.py
mlflow_extensions/databricks/deploy/gpu_configs.py
mlflow_extensions/databricks/deploy/utils.py
mlflow_extensions/databricks/prebuilt/__init__.py
mlflow_extensions/databricks/prebuilt/audio/__init__.py
mlflow_extensions/databricks/prebuilt/audio/vllm.py
mlflow_extensions/databricks/prebuilt/text/__init__.py
mlflow_extensions/databricks/prebuilt/text/sglang.py
mlflow_extensions/databricks/prebuilt/text/vllm.py
mlflow_extensions/databricks/prebuilt/vision/__init__.py
mlflow_extensions/databricks/prebuilt/vision/sglang.py
mlflow_extensions/databricks/prebuilt/vision/vllm.py
mlflow_extensions/log/__init__.py
mlflow_extensions/log/handlers.py
mlflow_extensions/serving/__init__.py
mlflow_extensions/serving/compute_details.py
mlflow_extensions/serving/fixtures.py
mlflow_extensions/serving/model.py
mlflow_extensions/serving/serde.py
mlflow_extensions/serving/serde_v2.py
mlflow_extensions/serving/wrapper.py
mlflow_extensions/serving/compat/__init__.py
mlflow_extensions/serving/compat/langchain.py
mlflow_extensions/serving/compat/openai.py
mlflow_extensions/serving/compat/sglang.py
mlflow_extensions/serving/engines/__init__.py
mlflow_extensions/serving/engines/base.py
mlflow_extensions/serving/engines/gpu_utils.py
mlflow_extensions/serving/engines/huggingface_utils.py
mlflow_extensions/serving/engines/mock_engine.py
mlflow_extensions/serving/engines/ollama_engine.py
mlflow_extensions/serving/engines/rayserve_engine.py
mlflow_extensions/serving/engines/sglang_engine.py
mlflow_extensions/serving/engines/vllm_engine.py
mlflow_extensions-0.17.1.dist-info/LICENSE
mlflow_extensions-0.17.1.dist-info/METADATA
mlflow_extensions-0.17.1.dist-info/WHEEL
mlflow_extensions-0.17.1.dist-info/top_level.txt
mlflow_extensions-0.17.1.dist-info/RECORD
