Metadata-Version: 2.1
Name: mlflow-extensions
Version: 0.17.1
Summary: Extensions for mlflow to make the devloop better for custom models.
Home-page: https://github.com/stikkireddy/mlflow-extensions
Author: Sri Tikkireddy
Author-email: sri.tikkireddy@databricks.com
Classifier: Programming Language :: Python :: 3
Classifier: License :: OSI Approved :: MIT License
Classifier: Operating System :: OS Independent
Requires-Python: >=3.10
License-File: LICENSE
Requires-Dist: databricks-sdk
Requires-Dist: filelock
Requires-Dist: httpx
Requires-Dist: huggingface-hub
Requires-Dist: mlflow-skinny[databricks] >=2.19.0
Requires-Dist: psutil
Requires-Dist: python-json-logger
Requires-Dist: structlog
Requires-Dist: tenacity
